sb_libs/__init__.py
sb_libs/testing/__init__.py
sb_libs/testing/__main__.py
sb_libs/testing/detect_unittest_usage.py
sb_libs/testing/naming_validator.py
sb_libs/testing/unittest_to_pytest_migrator.py
sb_libs_py-0.1.0.dist-info/METADATA
sb_libs_py-0.1.0.dist-info/WHEEL
sb_libs_py-0.1.0.dist-info/RECORD
