Metadata-Version: 2.4
Name: sb-libs-py
Version: 0.1.0
Summary: Python 라이브러리성 코드 공유용
Project-URL: Homepage, https://github.com/archmagece/scripton/sb-libs-py
Project-URL: Repository, https://github.com/archmagece/scripton/sb-libs-py
Author: archmagece
License-Expression: MIT
Classifier: Development Status :: 3 - Alpha
Classifier: Intended Audience :: Developers
Classifier: License :: OSI Approved :: MIT License
Classifier: Programming Language :: Python :: 3
Classifier: Programming Language :: Python :: 3.11
Classifier: Programming Language :: Python :: 3.12
Classifier: Programming Language :: Python :: 3.13
Requires-Python: >=3.11
Provides-Extra: dev
Requires-Dist: build>=1.2.2; extra == 'dev'
Requires-Dist: lxml>=5.2.0; extra == 'dev'
Requires-Dist: mypy>=1.16.1; extra == 'dev'
Requires-Dist: pre-commit>=4.2.0; extra == 'dev'
Requires-Dist: pytest-cov>=6.2.1; extra == 'dev'
Requires-Dist: pytest>=8.4.1; extra == 'dev'
Requires-Dist: ruff>=0.12.3; extra == 'dev'
Requires-Dist: twine>=6.1.0; extra == 'dev'
Provides-Extra: docs
Requires-Dist: sphinx-rtd-theme>=3.0.2; extra == 'docs'
Requires-Dist: sphinx>=8.2.3; extra == 'docs'
